market_data_pipeline/__init__.py
market_data_pipeline/config.py
market_data_pipeline/context.py
market_data_pipeline/errors.py
market_data_pipeline/metrics.py
market_data_pipeline/metrics_tick_analytics.py
market_data_pipeline/pacing.py
market_data_pipeline/pipeline.py
market_data_pipeline/pipeline_builder.py
market_data_pipeline/telemetry.py
market_data_pipeline/types.py
market_data_pipeline/adapters/__init__.py
market_data_pipeline/adapters/providers/__init__.py
market_data_pipeline/adapters/providers/ibkr_stream_source.py
market_data_pipeline/adapters/providers/provider_base.py
market_data_pipeline/adapters/providers/provider_registry.py
market_data_pipeline/api/__init__.py
market_data_pipeline/api/config_builders.py
market_data_pipeline/api/factory.py
market_data_pipeline/api/interface.py
market_data_pipeline/api/types.py
market_data_pipeline/api/validators.py
market_data_pipeline/batcher/__init__.py
market_data_pipeline/batcher/base.py
market_data_pipeline/batcher/hybrid.py
market_data_pipeline/cli/__init__.py
market_data_pipeline/cli/main.py
market_data_pipeline/jobs/__init__.py
market_data_pipeline/jobs/policies.py
market_data_pipeline/jobs/runner.py
market_data_pipeline/operator/__init__.py
market_data_pipeline/operator/bars.py
market_data_pipeline/operator/base.py
market_data_pipeline/operator/options.py
market_data_pipeline/orchestration/__init__.py
market_data_pipeline/orchestration/circuit_breaker.py
market_data_pipeline/orchestration/coordinator.py
market_data_pipeline/orchestration/ingest_orchestrator.py
market_data_pipeline/orchestration/registry.py
market_data_pipeline/orchestration/router.py
market_data_pipeline/orchestration/runtime.py
market_data_pipeline/orchestration/runtime_orchestrator.py
market_data_pipeline/orchestration/dag/__init__.py
market_data_pipeline/orchestration/dag/builder.py
market_data_pipeline/orchestration/dag/channel.py
market_data_pipeline/orchestration/dag/graph.py
market_data_pipeline/orchestration/dag/operators.py
market_data_pipeline-0.8.70.dist-info/METADATA
market_data_pipeline-0.8.70.dist-info/WHEEL
market_data_pipeline-0.8.70.dist-info/entry_points.txt
market_data_pipeline-0.8.70.dist-info/licenses/LICENSE
market_data_pipeline-0.8.70.dist-info/RECORD
