Metadata-Version: 2.4
Name: market_data_pipeline
Version: 0.8.70
Summary: Orchestration layer for market data pipelines
License-File: LICENSE
Requires-Python: >=3.11
Requires-Dist: aiofiles>=23.0.0
Requires-Dist: aiokafka>=0.8.0
Requires-Dist: asyncio-mqtt>=0.13.0
Requires-Dist: click>=8.1.0
Requires-Dist: core-registry-client==0.2.0
Requires-Dist: fastapi>=0.100.0
Requires-Dist: httpx>=0.24.0
Requires-Dist: jsonschema>=4.0.0
Requires-Dist: loguru>=0.7.0
Requires-Dist: market-data-core<2.0.0,>=1.4.61
Requires-Dist: numpy>=1.24.0
Requires-Dist: opentelemetry-api>=1.20.0
Requires-Dist: opentelemetry-instrumentation-fastapi>=0.41b0
Requires-Dist: opentelemetry-sdk>=1.20.0
Requires-Dist: pandas>=2.0.0
Requires-Dist: prometheus-client>=0.17.0
Requires-Dist: pyarrow>=12.0.0
Requires-Dist: pydantic-settings>=2.0.0
Requires-Dist: pydantic>=2.0.0
Requires-Dist: structlog>=23.0.0
Requires-Dist: tenacity>=8.2.0
Requires-Dist: uvicorn>=0.23.0
Provides-Extra: dag
Requires-Dist: mmh3>=4.0.1; extra == 'dag'
Provides-Extra: dev
Requires-Dist: black>=23.0.0; extra == 'dev'
Requires-Dist: freezegun>=1.2.0; extra == 'dev'
Requires-Dist: mypy>=1.5.0; extra == 'dev'
Requires-Dist: pytest-asyncio>=0.21.0; extra == 'dev'
Requires-Dist: pytest-cov>=4.1.0; extra == 'dev'
Requires-Dist: pytest>=7.4.0; extra == 'dev'
Requires-Dist: ruff>=0.0.280; extra == 'dev'
Provides-Extra: store
Requires-Dist: market-data-store>=1.0.0; extra == 'store'
